whois_format.py
whois_format-0.1.0a13.dist-info/LICENSE
whois_format-0.1.0a13.dist-info/METADATA
whois_format-0.1.0a13.dist-info/WHEEL
whois_format-0.1.0a13.dist-info/entry_points.txt
whois_format-0.1.0a13.dist-info/top_level.txt
whois_format-0.1.0a13.dist-info/RECORD
