Metadata-Version: 2.1
Name: whois-format
Version: 0.1.0a13
Summary: Whois client wrapper producing a terse, single-line format.
Author-email: Darren Spruell <phatbuckett@gmail.com>
Project-URL: Homepage, https://github.com/dspruell/whois-format/
Classifier: Development Status :: 3 - Alpha
Classifier: License :: OSI Approved :: ISC License (ISCL)
Classifier: Programming Language :: Python :: 3
License-File: LICENSE
Requires-Dist: python-whois
Requires-Dist: tabulate
